a7/__init__.py
a7/__main__.py
a7/validate.py
datadog_a7-0.0.8.dist-info/LICENSE
datadog_a7-0.0.8.dist-info/METADATA
datadog_a7-0.0.8.dist-info/WHEEL
datadog_a7-0.0.8.dist-info/entry_points.txt
datadog_a7-0.0.8.dist-info/top_level.txt
datadog_a7-0.0.8.dist-info/RECORD
